.DS_Store
easyfunctions/PySparkHelper.py
easyfunctions/WOEHelper.py
easyfunctions/__init__.py
easyfunctions/pandasDataFrameManipulator.py
easyfunctions-0.0.12.dist-info/METADATA
easyfunctions-0.0.12.dist-info/WHEEL
easyfunctions-0.0.12.dist-info/top_level.txt
easyfunctions-0.0.12.dist-info/RECORD
