Metadata-Version: 2.1
Name: easyfunctions
Version: 0.0.12
Summary: Package of helper objects that contain methods to process datasets and variables for data mining and statistical modeling
Home-page: https://gitlab.easytaxi.net.br/ops/gba/easy-analytics-dev-functions
Author: Data & Analytics Team @MaxiMobility Bogota
Author-email: jose.casas@easytaxi.com.co
License: UNKNOWN
Platform: UNKNOWN
Requires-Dist: pandas
Requires-Dist: numpy
